{
    "_runs_": {
        "run_1458312570_bbdcc488-cf94-4721-921e-6b2ae14708a4": {
            "downloading": {
                "gnos-download_time": 35, 
                "start": 1458437443, 
                "stop": 1458437479, 
                "time": 36
            }
        }
    }, 
    "aliquot_id": null, 
    "available_repos": [
        {
            "https://gtrepo-osdc-icgc.annailabs.com/": {
                "file_md5sum": "107805dd799f7868370e383054215dc2", 
                "file_size": 39911
            }
        }
    ], 
    "data_type": "Muse-VCF", 
    "files": [
        {
            "file_md5sum": "7bcf466930fa6f9a87ecbc0e7fe02e13", 
            "file_name": "6dbac113-d4cf-4db5-97c9-50fa400bb47e.MUSE_1-0rc-b391201-vcf.20151218.somatic.snv_mnv.vcf.gz", 
            "file_size": 347267, 
            "object_id": "e6633453-f9a1-5f0d-a123-c201ce57105a"
        }, 
        {
            "file_md5sum": "dfd4cae592486c50c68d5512a7ea2c00", 
            "file_name": "6dbac113-d4cf-4db5-97c9-50fa400bb47e.MUSE_1-0rc-b391201-vcf.20151218.somatic.snv_mnv.vcf.gz.idx", 
            "file_size": 181911, 
            "object_id": "d08a79cf-86c5-5919-96a3-17c07ba0bfee"
        }, 
        {
            "file_md5sum": "107805dd799f7868370e383054215dc2", 
            "file_name": "2ce86f6e-cf1a-4326-9a11-95c0e5fd6c92.xml", 
            "file_size": 39911, 
            "object_id": "4bfbb0cf-d7b3-5850-8545-0dcce29107fc"
        }
    ], 
    "gnos_id": "2ce86f6e-cf1a-4326-9a11-95c0e5fd6c92", 
    "gnos_repo": [
        "https://gtrepo-osdc-icgc.annailabs.com/"
    ], 
    "project_code": "GACA-CN", 
    "specimen_type": null, 
    "submitter_donor_id": "CGP_donor_GC00005", 
    "submitter_sample_id": null, 
    "submitter_specimen_id": null, 
    "vcf_workflow_result_version": "v1"
}