{
    "_runs_": {
        "run_1458273978_aad05114-7fe8-4bf7-a139-3ad15ff6635c": {
            "downloading": {
                "gnos-download_time": 120, 
                "start": 1458277826, 
                "stop": 1458277947, 
                "time": 121
            }
        }
    }, 
    "aliquot_id": null, 
    "available_repos": [
        {
            "https://gtrepo-osdc-icgc.annailabs.com/": {
                "file_md5sum": "5adc2ecfe447efb28604eb7f9156c479", 
                "file_size": 36522
            }
        }
    ], 
    "data_type": "Muse-VCF", 
    "files": [
        {
            "file_md5sum": "499d2463a08f8a1019b125166f23d840", 
            "file_name": "9be1246b-3dc1-4928-8b89-2d5ed0c866e8.MUSE_1-0rc-vcf.20151023.somatic.snv_mnv.vcf.gz", 
            "file_size": 107665, 
            "object_id": ""
        }, 
        {
            "file_md5sum": "774b06354055eb5edf973eed4e0423c6", 
            "file_name": "9be1246b-3dc1-4928-8b89-2d5ed0c866e8.MUSE_1-0rc-vcf.20151023.somatic.snv_mnv.vcf.gz.idx", 
            "file_size": 58480, 
            "object_id": ""
        }, 
        {
            "file_md5sum": "5adc2ecfe447efb28604eb7f9156c479", 
            "file_name": "778c9a53-ad00-4e62-816a-d06239d0009a.xml", 
            "file_size": 36522, 
            "object_id": ""
        }
    ], 
    "gnos_id": "778c9a53-ad00-4e62-816a-d06239d0009a", 
    "gnos_repo": [
        "https://gtrepo-osdc-icgc.annailabs.com/"
    ], 
    "project_code": "PBCA-DE", 
    "specimen_type": null, 
    "submitter_donor_id": "ICGC_MB66", 
    "submitter_sample_id": null, 
    "submitter_specimen_id": null, 
    "vcf_workflow_result_version": "v1"
}