{
    "_runs_": {
        "run_1458274028_b58502af-0f02-42d1-9045-12ca0278f07e": {
            "downloading": {
                "gnos-download_time": 131, 
                "start": 1458282405, 
                "stop": 1458282536, 
                "time": 131
            }, 
            "uploading": {
                "copy_meta_time": 2, 
                "start": 1458282548, 
                "stop": 1458282592, 
                "time": 44, 
                "upload_time": 42
            }
        }
    }, 
    "aliquot_id": null, 
    "available_repos": [
        {
            "https://gtrepo-osdc-icgc.annailabs.com/": {
                "file_md5sum": "41641c0f4dc7f68586479804dfe9f609", 
                "file_size": 34037
            }
        }
    ], 
    "data_type": "Muse-VCF", 
    "files": [
        {
            "file_md5sum": "40d7075cf118a873a4ff085d3542d1f9", 
            "file_name": "b8270565-9e02-4d46-9534-08206bfd027a.MUSE_1-0rc-b391201-vcf.20151219.somatic.snv_mnv.vcf.gz", 
            "file_size": 115025, 
            "object_id": "af5c640e-39ac-5715-ae87-a6b54f77fbb3"
        }, 
        {
            "file_md5sum": "798022603b0c00b2c6a01a4c18e7e173", 
            "file_name": "b8270565-9e02-4d46-9534-08206bfd027a.MUSE_1-0rc-b391201-vcf.20151219.somatic.snv_mnv.vcf.gz.idx", 
            "file_size": 63739, 
            "object_id": "420e18f8-d3a0-5e81-b90a-5827cc03b136"
        }, 
        {
            "file_md5sum": "41641c0f4dc7f68586479804dfe9f609", 
            "file_name": "8ffe99b2-1405-4dbf-a244-9e3dc1789a4d.xml", 
            "file_size": 34037, 
            "object_id": "1654ee56-4510-5b3c-84e5-5009813598fa"
        }
    ], 
    "gnos_id": "8ffe99b2-1405-4dbf-a244-9e3dc1789a4d", 
    "gnos_repo": [
        "https://gtrepo-osdc-icgc.annailabs.com/"
    ], 
    "project_code": "PACA-CA", 
    "specimen_type": null, 
    "submitter_donor_id": "PCSI_0527", 
    "submitter_sample_id": null, 
    "submitter_specimen_id": null, 
    "vcf_workflow_result_version": "v1"
}