{
    "_runs_": {
        "run_1458274128_7a45ecdc-f5a1-4001-b5db-c2472847dad9": {
            "downloading": {
                "gnos-download_time": 121, 
                "start": 1458275274, 
                "stop": 1458275397, 
                "time": 123
            }, 
            "uploading": {
                "copy_meta_time": 1, 
                "start": 1458275407, 
                "stop": 1458275445, 
                "time": 38, 
                "upload_time": 37
            }
        }
    }, 
    "aliquot_id": null, 
    "available_repos": [
        {
            "https://gtrepo-osdc-icgc.annailabs.com/": {
                "file_md5sum": "8988d461e77fcdc937fb72dd13a8477d", 
                "file_size": 36258
            }
        }
    ], 
    "data_type": "Muse-VCF", 
    "files": [
        {
            "file_md5sum": "e70f3c8ad08dad1315458c871678ec22", 
            "file_name": "bcc819eb-f4d8-4ddc-9fdc-a6307fb6741b.MUSE_1-0rc-vcf.20151215.somatic.snv_mnv.vcf.gz", 
            "file_size": 200342, 
            "object_id": "6ff8c867-2032-5e9b-bedb-edc2ee5ccbeb"
        }, 
        {
            "file_md5sum": "75cd44660069ead2c35dab22ca4bb32e", 
            "file_name": "bcc819eb-f4d8-4ddc-9fdc-a6307fb6741b.MUSE_1-0rc-vcf.20151215.somatic.snv_mnv.vcf.gz.idx", 
            "file_size": 103374, 
            "object_id": "e868e0b7-101a-5e36-9ff0-68553937fcdf"
        }, 
        {
            "file_md5sum": "8988d461e77fcdc937fb72dd13a8477d", 
            "file_name": "a0c86772-7af6-42dc-b98b-d660509158be.xml", 
            "file_size": 36258, 
            "object_id": "bed3bd2c-041c-5201-9902-f967ba850d97"
        }
    ], 
    "gnos_id": "a0c86772-7af6-42dc-b98b-d660509158be", 
    "gnos_repo": [
        "https://gtrepo-osdc-icgc.annailabs.com/"
    ], 
    "project_code": "ORCA-IN", 
    "specimen_type": null, 
    "submitter_donor_id": "OSCC-GB_012601", 
    "submitter_sample_id": null, 
    "submitter_specimen_id": null, 
    "vcf_workflow_result_version": "v1"
}