{
    "_runs_": {
        "run_1457961381_43e050fd-d73a-48cd-a551-2cc1b1c15018": {
            "downloading": {
                "gnos-download_time": 94, 
                "start": 1457976650, 
                "stop": 1457976745, 
                "time": 95
            }, 
            "uploading": {
                "copy_meta_time": 1, 
                "start": 1457976763, 
                "stop": 1457976788, 
                "time": 25, 
                "upload_time": 24
            }
        }
    }, 
    "aliquot_id": null, 
    "available_repos": [
        {
            "https://gtrepo-osdc-icgc.annailabs.com/": {
                "file_md5sum": "6ddc2838b86d440b17f8e61851ac1d96", 
                "file_size": 36278
            }
        }
    ], 
    "data_type": "Muse-VCF", 
    "files": [
        {
            "file_md5sum": "0290e32fed232efb086d1cde89d11c71", 
            "file_name": "bb45c6f5-49cb-418d-85bb-3ded165e2d07.MUSE_1-0rc-vcf.20151023.somatic.snv_mnv.vcf.gz", 
            "file_size": 51552, 
            "object_id": "1ba9f7e2-90a2-5d51-818b-24b6e5ae0a5b"
        }, 
        {
            "file_md5sum": "d83de9933976e75a29e8cb9559afb7b0", 
            "file_name": "bb45c6f5-49cb-418d-85bb-3ded165e2d07.MUSE_1-0rc-vcf.20151023.somatic.snv_mnv.vcf.gz.idx", 
            "file_size": 29568, 
            "object_id": "9864f855-10e3-58d7-9a89-5bac2fbafc00"
        }, 
        {
            "file_md5sum": "6ddc2838b86d440b17f8e61851ac1d96", 
            "file_name": "d6c3add2-c3c5-4563-bfb6-f992dad929fe.xml", 
            "file_size": 36278, 
            "object_id": "86182c21-ed49-50c2-8c0e-24557d34de6a"
        }
    ], 
    "gnos_id": "d6c3add2-c3c5-4563-bfb6-f992dad929fe", 
    "gnos_repo": [
        "https://gtrepo-osdc-icgc.annailabs.com/"
    ], 
    "project_code": "PBCA-DE", 
    "specimen_type": null, 
    "submitter_donor_id": "ICGC_PA159", 
    "submitter_sample_id": null, 
    "submitter_specimen_id": null, 
    "vcf_workflow_result_version": "v1"
}