{
    "aliquot_id": null, 
    "available_repos": [
        {
            "https://gtrepo-osdc-icgc.annailabs.com/": {
                "file_md5sum": "ef4534e9de13127157ae7105c14f3e90", 
                "file_size": 36136
            }
        }
    ], 
    "data_type": "Muse-VCF", 
    "files": [
        {
            "file_md5sum": "e4edc46355ecdd34b1e0782f607452b1", 
            "file_name": "d4ecbf52-f6a9-4394-9d3b-8eb8eee1b17b.MUSE_1-0rc-vcf.20151023.somatic.snv_mnv.vcf.gz", 
            "file_size": 46535, 
            "object_id": "4387afeb-9f3b-5a79-a32b-956e6f30f241"
        }, 
        {
            "file_md5sum": "7a5f7aa4c259ac5e53c6e5ee45d66c79", 
            "file_name": "d4ecbf52-f6a9-4394-9d3b-8eb8eee1b17b.MUSE_1-0rc-vcf.20151023.somatic.snv_mnv.vcf.gz.idx", 
            "file_size": 27808, 
            "object_id": "6a633523-fde7-56dd-aeff-1a52d2a5b6c7"
        }, 
        {
            "file_md5sum": "ef4534e9de13127157ae7105c14f3e90", 
            "file_name": "c1fbcbd6-9bf6-4f9c-a994-d5d896d6b169.xml", 
            "file_size": 36136, 
            "object_id": "095a4ddd-834d-56e5-af3a-12094ffd076c"
        }
    ], 
    "gnos_id": "c1fbcbd6-9bf6-4f9c-a994-d5d896d6b169", 
    "gnos_repo": [
        "https://gtrepo-osdc-icgc.annailabs.com/"
    ], 
    "project_code": "PBCA-DE", 
    "specimen_type": null, 
    "submitter_donor_id": "ICGC_PA163", 
    "submitter_sample_id": null, 
    "submitter_specimen_id": null, 
    "vcf_workflow_result_version": "v1"
}