{
    "_runs_": {
        "run_1473902250_33ebbabb-ee98-4fda-b970-a70923e192bc": {
            "downloading": {
                "gnos-download_time": 17, 
                "start": 1473907636, 
                "stop": 1473907653, 
                "time": 17
            }
        }
    }, 
    "aliquot_id": "3e7ccab5-5b1d-4147-b907-77cab8f0837e", 
    "available_repos": [
        {
            "https://gtrepo-osdc-icgc.annailabs.com/": {
                "file_md5sum": "7610da090085cd8ad26e33e56d09a3de", 
                "file_size": 34552
            }
        }
    ], 
    "data_type": "Consensus-somatic-SNV_MNV", 
    "files": [
        {
            "file_md5sum": "5b60184e914c3114d9795330d8cc5ed2", 
            "file_name": "3e7ccab5-5b1d-4147-b907-77cab8f0837e.consensus.20160830.somatic.snv_mnv.vcf.gz", 
            "file_size": 237603, 
            "object_id": "516b2b26-9268-5ada-89c2-9e436752d7c1"
        }, 
        {
            "file_md5sum": "65faf8a6ef3b60f0c4ece83d4bd627a3", 
            "file_name": "3e7ccab5-5b1d-4147-b907-77cab8f0837e.consensus.20160830.somatic.snv_mnv.vcf.gz.tbi", 
            "file_size": 125216, 
            "object_id": "e74e2d6c-baf8-5f05-8850-4acace1863e3"
        }, 
        {
            "file_md5sum": "7610da090085cd8ad26e33e56d09a3de", 
            "file_name": "104a144b-d5be-4cd0-9c1e-41ccd5037ee7.xml", 
            "file_size": 34552, 
            "object_id": "3ede99b4-d3aa-518e-b9ff-54621fee4b87"
        }
    ], 
    "gnos_id": "104a144b-d5be-4cd0-9c1e-41ccd5037ee7", 
    "gnos_repo": [
        "https://gtrepo-osdc-icgc.annailabs.com/"
    ], 
    "project_code": "MALY-DE", 
    "specimen_type": null, 
    "submitter_donor_id": "4136702", 
    "submitter_sample_id": null, 
    "submitter_specimen_id": "3e7ccab5-5b1d-4147-b907-77cab8f0837e", 
    "vcf_workflow_result_version": "v1"
}