{
    "_runs_": {
        "run_1473902443_d1e1ef91-aef7-429e-aa84-08094051c063": {
            "downloading": {
                "gnos-download_time": 29, 
                "start": 1473910426, 
                "stop": 1473910455, 
                "time": 29
            }
        }
    }, 
    "aliquot_id": "fc8130e0-a38a-23b9-e040-11ac0c48327f", 
    "available_repos": [
        {
            "https://gtrepo-osdc-icgc.annailabs.com/": {
                "file_md5sum": "93a9e1bc796116bad32b606105f183a2", 
                "file_size": 32510
            }
        }
    ], 
    "data_type": "Consensus-somatic-SNV_MNV", 
    "files": [
        {
            "file_md5sum": "20eb3999a263d8ac13892ad0c260dd4c", 
            "file_name": "fc8130e0-a38a-23b9-e040-11ac0c48327f.consensus.20160830.somatic.snv_mnv.vcf.gz", 
            "file_size": 246109, 
            "object_id": "dc7dd635-7b1a-59da-90c2-2b00d1c4baf3"
        }, 
        {
            "file_md5sum": "392af8954df2d0f461a6f5e72fac3376", 
            "file_name": "fc8130e0-a38a-23b9-e040-11ac0c48327f.consensus.20160830.somatic.snv_mnv.vcf.gz.tbi", 
            "file_size": 133695, 
            "object_id": "a3e02293-7f33-556b-8ec4-fa1f000503fb"
        }, 
        {
            "file_md5sum": "93a9e1bc796116bad32b606105f183a2", 
            "file_name": "19d63fbe-6e39-42cc-a9b9-836da3cd08bd.xml", 
            "file_size": 32510, 
            "object_id": "81570857-0d87-5ed7-b167-9e2fe3d21898"
        }
    ], 
    "gnos_id": "19d63fbe-6e39-42cc-a9b9-836da3cd08bd", 
    "gnos_repo": [
        "https://gtrepo-osdc-icgc.annailabs.com/"
    ], 
    "project_code": "BRCA-EU", 
    "specimen_type": null, 
    "submitter_donor_id": "CGP_donor_1234120", 
    "submitter_sample_id": null, 
    "submitter_specimen_id": "fc8130e0-a38a-23b9-e040-11ac0c48327f", 
    "vcf_workflow_result_version": "v1"
}