{
    "_runs_": {
        "run_1473902250_33ebbabb-ee98-4fda-b970-a70923e192bc": {
            "downloading": {
                "gnos-download_time": 24, 
                "start": 1473913375, 
                "stop": 1473913399, 
                "time": 24
            }
        }
    }, 
    "aliquot_id": "8cbd1752-7eea-46d3-8623-09e96dfb1fdf", 
    "available_repos": [
        {
            "https://gtrepo-osdc-icgc.annailabs.com/": {
                "file_md5sum": "54b5f5d129b45eee4b8828ac9ddd2136", 
                "file_size": 31493
            }
        }
    ], 
    "data_type": "Consensus-somatic-INDEL", 
    "files": [
        {
            "file_md5sum": "daec68a6e8b654aeedee8b90a9630789", 
            "file_name": "8cbd1752-7eea-46d3-8623-09e96dfb1fdf.consensus.20160830.somatic.indel.vcf.gz", 
            "file_size": 34194, 
            "object_id": "cac7090d-67dd-55d9-a3ed-3f9dab7d1ccd"
        }, 
        {
            "file_md5sum": "7c68065fcf9942bf8eb06b858aaf10a2", 
            "file_name": "8cbd1752-7eea-46d3-8623-09e96dfb1fdf.consensus.20160830.somatic.indel.vcf.gz.tbi", 
            "file_size": 16448, 
            "object_id": "bc1e3092-a94b-5817-80f7-e24dc1a3c216"
        }, 
        {
            "file_md5sum": "54b5f5d129b45eee4b8828ac9ddd2136", 
            "file_name": "2958d544-1ffe-435f-a5f0-7dcb67bdbc93.xml", 
            "file_size": 31493, 
            "object_id": "8f409179-128a-519a-a07f-91cdfcc22d40"
        }
    ], 
    "gnos_id": "2958d544-1ffe-435f-a5f0-7dcb67bdbc93", 
    "gnos_repo": [
        "https://gtrepo-osdc-icgc.annailabs.com/"
    ], 
    "project_code": "PAEN-IT", 
    "specimen_type": null, 
    "submitter_donor_id": "ITNET-0124", 
    "submitter_sample_id": null, 
    "submitter_specimen_id": "8cbd1752-7eea-46d3-8623-09e96dfb1fdf", 
    "vcf_workflow_result_version": "v1"
}