{
    "_runs_": {
        "run_1492782075_4182bd23-02d1-40e7-a480-3645e746f787": {
            "downloading": {
                "gnos-download_time": 24, 
                "start": 1492796760, 
                "stop": 1492796784, 
                "time": 24
            }
        }
    }, 
    "aliquot_id": "2c2e5f87-bd22-4a5e-be71-3bcc2aefaf74", 
    "available_repos": [
        {
            "https://gtrepo-osdc-icgc.annailabs.com/": {
                "file_md5sum": "077216c3fbc865cbd3c540d6fc4a6fbe", 
                "file_size": 32654
            }
        }
    ], 
    "data_type": "Consensus-somatic-INDEL", 
    "files": [
        {
            "file_md5sum": "5f0d4683a53eb5c7b365257aa9f49e5b", 
            "file_name": "2c2e5f87-bd22-4a5e-be71-3bcc2aefaf74.consensus.20161006.somatic.indel.vcf.gz", 
            "file_size": 16232, 
            "object_id": "c0705600-fc3c-5ed8-b30e-1a29afb4ab3b"
        }, 
        {
            "file_md5sum": "82d438ae83288d1ac31e58572175ab61", 
            "file_name": "2c2e5f87-bd22-4a5e-be71-3bcc2aefaf74.consensus.20161006.somatic.indel.vcf.gz.tbi", 
            "file_size": 9580, 
            "object_id": "52a3a022-b42c-5d4f-b864-2de2af8397b7"
        }, 
        {
            "file_md5sum": "077216c3fbc865cbd3c540d6fc4a6fbe", 
            "file_name": "2f8aef05-f204-4a26-ad97-53976df9d060.xml", 
            "file_size": 32654, 
            "object_id": "cf26fccb-f3f8-5b3b-b73f-e97dbbc59e90"
        }
    ], 
    "gnos_id": "2f8aef05-f204-4a26-ad97-53976df9d060", 
    "gnos_repo": [
        "https://gtrepo-osdc-icgc.annailabs.com/"
    ], 
    "project_code": "PBCA-DE", 
    "specimen_type": null, 
    "submitter_donor_id": "ICGC_PA43", 
    "submitter_sample_id": null, 
    "submitter_specimen_id": "2c2e5f87-bd22-4a5e-be71-3bcc2aefaf74", 
    "vcf_workflow_result_version": "v1"
}