{
    "_runs_": {
        "run_1493040506_52bf6ac5-3c00-4459-9c7f-dd167227085d": {
            "downloading": {
                "gnos-download_time": 34, 
                "gtdownload-error": true, 
                "start": 1493040976, 
                "stop": 1493041010, 
                "time": 34
            }
        }, 
        "run_1493731661_39888e7a-47aa-46d8-8cc8-83bd77bce168": {
            "downloading": {
                "gnos-download_time": 19, 
                "start": 1493825034, 
                "stop": 1493825053, 
                "time": 19
            }
        }
    }, 
    "aliquot_id": "dccddb92-bb26-4dc9-a935-2320d089a54a", 
    "available_repos": [
        {
            "https://gtrepo-osdc-icgc.annailabs.com/": {
                "file_md5sum": "983c1fc5d8973c1c740f5ea168f2d964", 
                "file_size": 32524
            }
        }
    ], 
    "data_type": "Consensus-somatic-INDEL", 
    "files": [
        {
            "file_md5sum": "eeff08d225ae840ab5364d1befebc7e5", 
            "file_name": "dccddb92-bb26-4dc9-a935-2320d089a54a.consensus.20161006.somatic.indel.vcf.gz", 
            "file_size": 25261, 
            "object_id": "b1c2a312-4465-5625-b5b8-e8c7f6bc8cc9"
        }, 
        {
            "file_md5sum": "7b8bc9778779a3c3276ab708ea118e64", 
            "file_name": "dccddb92-bb26-4dc9-a935-2320d089a54a.consensus.20161006.somatic.indel.vcf.gz.tbi", 
            "file_size": 13276, 
            "object_id": "0175fc2a-92fd-596b-b791-2e9e894d6b14"
        }, 
        {
            "file_md5sum": "983c1fc5d8973c1c740f5ea168f2d964", 
            "file_name": "540d94f2-0cfd-47bf-bbbd-eb11c62e4bed.xml", 
            "file_size": 32524, 
            "object_id": "015cceee-1f57-597e-856c-6552a618f9d1"
        }
    ], 
    "gnos_id": "540d94f2-0cfd-47bf-bbbd-eb11c62e4bed", 
    "gnos_repo": [
        "https://gtrepo-osdc-icgc.annailabs.com/"
    ], 
    "project_code": "PBCA-DE", 
    "specimen_type": null, 
    "submitter_donor_id": "ICGC_PA165", 
    "submitter_sample_id": null, 
    "submitter_specimen_id": "dccddb92-bb26-4dc9-a935-2320d089a54a", 
    "vcf_workflow_result_version": "v1"
}