{
    "_runs_": {
        "run_1493648426_0d2c4d64-eee6-4713-974c-a437f69cff2b": {
            "downloading": {
                "gnos-download_time": 24, 
                "start": 1493651495, 
                "stop": 1493651519, 
                "time": 24
            }
        }
    }, 
    "aliquot_id": "2a5a5840-a834-47a1-b1f4-dc8fed620f5c", 
    "available_repos": [
        {
            "https://gtrepo-osdc-icgc.annailabs.com/": {
                "file_md5sum": "679892083036cbd5b3f165543b684924", 
                "file_size": 32796
            }
        }
    ], 
    "data_type": "Consensus-somatic-INDEL", 
    "files": [
        {
            "file_md5sum": "c03ce1322fb928e55b4a9fc736cf4789", 
            "file_name": "2a5a5840-a834-47a1-b1f4-dc8fed620f5c.consensus.20161006.somatic.indel.vcf.gz", 
            "file_size": 16859, 
            "object_id": "52936e6d-bb4a-507e-ae8b-26dcb8cb9dfa"
        }, 
        {
            "file_md5sum": "182e8fc0bdb91ed51836da9f6c2028b6", 
            "file_name": "2a5a5840-a834-47a1-b1f4-dc8fed620f5c.consensus.20161006.somatic.indel.vcf.gz.tbi", 
            "file_size": 9746, 
            "object_id": "def5230f-2e54-5e49-87ca-f3dabad46d26"
        }, 
        {
            "file_md5sum": "679892083036cbd5b3f165543b684924", 
            "file_name": "5a7bd85b-a7d6-4db6-bd90-5cc8a029ded5.xml", 
            "file_size": 32796, 
            "object_id": "6a48a24a-a5f4-5141-b195-31483b65c1ce"
        }
    ], 
    "gnos_id": "5a7bd85b-a7d6-4db6-bd90-5cc8a029ded5", 
    "gnos_repo": [
        "https://gtrepo-osdc-icgc.annailabs.com/"
    ], 
    "project_code": "PBCA-DE", 
    "specimen_type": null, 
    "submitter_donor_id": "ICGC_PA73", 
    "submitter_sample_id": null, 
    "submitter_specimen_id": "2a5a5840-a834-47a1-b1f4-dc8fed620f5c", 
    "vcf_workflow_result_version": "v1"
}