{
    "_runs_": {
        "run_1493731661_39888e7a-47aa-46d8-8cc8-83bd77bce168": {
            "downloading": {
                "gnos-download_time": 26, 
                "start": 1493750079, 
                "stop": 1493750105, 
                "time": 26
            }, 
            "uploading": {
                "copy_meta_time": 2, 
                "start": 1493750111, 
                "stop": 1493750139, 
                "time": 28, 
                "upload_time": 26
            }
        }
    }, 
    "aliquot_id": "fc8130df-6977-7704-e040-11ac0d485de4", 
    "available_repos": [
        {
            "https://gtrepo-osdc-icgc.annailabs.com/": {
                "file_md5sum": "cf0213967269bd82e3969c0f1f942ba0", 
                "file_size": 33255
            }
        }
    ], 
    "data_type": "Consensus-somatic-INDEL", 
    "files": [
        {
            "file_md5sum": "204db4bac20527cd578b1778e3d5f2b2", 
            "file_name": "fc8130df-6977-7704-e040-11ac0d485de4.consensus.20161006.somatic.indel.vcf.gz", 
            "file_size": 17814, 
            "object_id": "0133dad2-1a6f-5d71-99c6-c37bab377ee5"
        }, 
        {
            "file_md5sum": "adc3243b6813f2689a54e579b5589391", 
            "file_name": "fc8130df-6977-7704-e040-11ac0d485de4.consensus.20161006.somatic.indel.vcf.gz.tbi", 
            "file_size": 10717, 
            "object_id": "d126d364-4eac-5387-9c49-bb691f426e57"
        }, 
        {
            "file_md5sum": "cf0213967269bd82e3969c0f1f942ba0", 
            "file_name": "a399e20f-69a2-4a1d-9553-f068cff4b8a3.xml", 
            "file_size": 33255, 
            "object_id": "fbb82823-70f2-51a7-9f8c-15c554151ffb"
        }
    ], 
    "gnos_id": "a399e20f-69a2-4a1d-9553-f068cff4b8a3", 
    "gnos_repo": [
        "https://gtrepo-osdc-icgc.annailabs.com/"
    ], 
    "project_code": "BRCA-EU", 
    "specimen_type": null, 
    "submitter_donor_id": "CGP_donor_1337220", 
    "submitter_sample_id": null, 
    "submitter_specimen_id": "fc8130df-6977-7704-e040-11ac0d485de4", 
    "vcf_workflow_result_version": "v1"
}