{
    "_runs_": {
        "run_1493731661_39888e7a-47aa-46d8-8cc8-83bd77bce168": {
            "downloading": {
                "gnos-download_time": 23, 
                "start": 1493797582, 
                "stop": 1493797606, 
                "time": 24
            }, 
            "uploading": {
                "copy_meta_time": 2, 
                "start": 1493797612, 
                "stop": 1493797638, 
                "time": 26, 
                "upload_time": 24
            }
        }
    }, 
    "aliquot_id": "2abe2e53-ad9b-4fbc-b9a7-93444f1bea87", 
    "available_repos": [
        {
            "https://gtrepo-osdc-icgc.annailabs.com/": {
                "file_md5sum": "d0e192f05d7513597948168197e2c296", 
                "file_size": 32485
            }
        }
    ], 
    "data_type": "Consensus-somatic-INDEL", 
    "files": [
        {
            "file_md5sum": "7be58f2becd7747fdce204cd9762a8ee", 
            "file_name": "2abe2e53-ad9b-4fbc-b9a7-93444f1bea87.consensus.20161006.somatic.indel.vcf.gz", 
            "file_size": 46245, 
            "object_id": "958dbdf9-4de3-5942-8ce4-5a4053639bb2"
        }, 
        {
            "file_md5sum": "ea0b25e225ebdcf5ea7f755f9a43be3a", 
            "file_name": "2abe2e53-ad9b-4fbc-b9a7-93444f1bea87.consensus.20161006.somatic.indel.vcf.gz.tbi", 
            "file_size": 22990, 
            "object_id": "d8fc3e46-40da-59e9-997a-93536735902d"
        }, 
        {
            "file_md5sum": "d0e192f05d7513597948168197e2c296", 
            "file_name": "fea49b00-3cc8-4c85-88f6-b408ebc02f4d.xml", 
            "file_size": 32485, 
            "object_id": "56f4e89b-ef51-52b8-ade6-c0d21debcff5"
        }
    ], 
    "gnos_id": "fea49b00-3cc8-4c85-88f6-b408ebc02f4d", 
    "gnos_repo": [
        "https://gtrepo-osdc-icgc.annailabs.com/"
    ], 
    "project_code": "PBCA-DE", 
    "specimen_type": null, 
    "submitter_donor_id": "ICGC_MB56", 
    "submitter_sample_id": null, 
    "submitter_specimen_id": "2abe2e53-ad9b-4fbc-b9a7-93444f1bea87", 
    "vcf_workflow_result_version": "v1"
}