{
    "_runs_": {
        "run_1458274444_5014f649-97e8-4531-9642-23d86f721786": {
            "downloading": {
                "gnos-download_time": 128, 
                "start": 1458283906, 
                "stop": 1458284035, 
                "time": 129
            }
        }
    }, 
    "aliquot_id": null, 
    "available_repos": [
        {
            "https://gtrepo-osdc-icgc.annailabs.com/": {
                "file_md5sum": "2d4bc529ccc6e3d6f24b83b8bb154c97", 
                "file_size": 39532
            }
        }
    ], 
    "data_type": "Broad-VCF", 
    "files": [
        {
            "file_md5sum": "904423ad28e286f8f44b1864c01dfd30", 
            "file_name": "2e76891c-b620-4cc0-9315-6f1217b09b1e.broad-mutect-v3.20160222.somatic.snv_mnv.vcf.gz.idx", 
            "file_size": 448646, 
            "object_id": ""
        }, 
        {
            "file_md5sum": "027f16ea6a9f2133822951f686eec571", 
            "file_name": "2e76891c-b620-4cc0-9315-6f1217b09b1e.broad-mutect-v3.20160222.somatic.snv_mnv.vcf.gz", 
            "file_size": 1577973, 
            "object_id": ""
        }, 
        {
            "file_md5sum": "0d6874751ea8ea1496bb0397711d38ce", 
            "file_name": "2e76891c-b620-4cc0-9315-6f1217b09b1e.broad-snowman-10.20151218.germline.sv.vcf.gz.idx", 
            "file_size": 53229, 
            "object_id": ""
        }, 
        {
            "file_md5sum": "068c6c28f78aa187d181952fecfc8c81", 
            "file_name": "2e76891c-b620-4cc0-9315-6f1217b09b1e.broad-snowman-10.20151218.germline.sv.vcf.gz", 
            "file_size": 1658068, 
            "object_id": ""
        }, 
        {
            "file_md5sum": "cde7e4801795a2839708d1396e403b1a", 
            "file_name": "2e76891c-b620-4cc0-9315-6f1217b09b1e.broad-snowman-10.20151218.somatic.indel.vcf.gz", 
            "file_size": 56588, 
            "object_id": ""
        }, 
        {
            "file_md5sum": "59b16a1b13ec2f967cb21c0102f3b933", 
            "file_name": "2e76891c-b620-4cc0-9315-6f1217b09b1e.broad-dRanger_snowman-10.20151218.somatic.sv.vcf.gz", 
            "file_size": 74760, 
            "object_id": ""
        }, 
        {
            "file_md5sum": "b55aad7c7670b51b3a2f448a1583fc5d", 
            "file_name": "2e76891c-b620-4cc0-9315-6f1217b09b1e.broad-snowman-10.20151218.somatic.sv.vcf.gz.idx", 
            "file_size": 7120, 
            "object_id": ""
        }, 
        {
            "file_md5sum": "aaa1f5a927d37df71b94612b90f367d6", 
            "file_name": "2e76891c-b620-4cc0-9315-6f1217b09b1e.broad-snowman-10.20151218.somatic.sv.vcf.gz", 
            "file_size": 72991, 
            "object_id": ""
        }, 
        {
            "file_md5sum": "267fcf5f75fe9f4dd35a83ec2cbe63ec", 
            "file_name": "2e76891c-b620-4cc0-9315-6f1217b09b1e.broad-snowman-10.20151218.germline.indel.vcf.gz.idx", 
            "file_size": 1003890, 
            "object_id": ""
        }, 
        {
            "file_md5sum": "52c46669f4bd5df6fe89bfd421a36aa4", 
            "file_name": "2e76891c-b620-4cc0-9315-6f1217b09b1e.broad-dRanger-10.20151218.somatic.sv.vcf.gz.idx", 
            "file_size": 2097, 
            "object_id": ""
        }, 
        {
            "file_md5sum": "937b58b82ad90076aec97a68d26d55dc", 
            "file_name": "2e76891c-b620-4cc0-9315-6f1217b09b1e.broad-snowman-10.20151218.somatic.indel.vcf.gz.idx", 
            "file_size": 21264, 
            "object_id": ""
        }, 
        {
            "file_md5sum": "71f849f4c0b988be4c0fad26e903b71e", 
            "file_name": "2e76891c-b620-4cc0-9315-6f1217b09b1e.broad-dRanger_snowman-10.20151218.somatic.sv.vcf.gz.idx", 
            "file_size": 7166, 
            "object_id": ""
        }, 
        {
            "file_md5sum": "42b3e5e7c8953e670ca09acefbd970fb", 
            "file_name": "2e76891c-b620-4cc0-9315-6f1217b09b1e.broad-snowman-10.20151218.germline.indel.vcf.gz", 
            "file_size": 10352772, 
            "object_id": ""
        }, 
        {
            "file_md5sum": "ced6e42795c32c3a7bf518ed2bdffc69", 
            "file_name": "2e76891c-b620-4cc0-9315-6f1217b09b1e.broad-dRanger-10.20151218.somatic.sv.vcf.gz", 
            "file_size": 14946, 
            "object_id": ""
        }, 
        {
            "file_md5sum": "2d4bc529ccc6e3d6f24b83b8bb154c97", 
            "file_name": "32edb572-2145-493f-93d3-4cb79255e7a4.xml", 
            "file_size": 39532, 
            "object_id": ""
        }
    ], 
    "gnos_id": "32edb572-2145-493f-93d3-4cb79255e7a4", 
    "gnos_repo": [
        "https://gtrepo-osdc-icgc.annailabs.com/"
    ], 
    "project_code": "MELA-AU", 
    "specimen_type": null, 
    "submitter_donor_id": "MELA-0160", 
    "submitter_sample_id": null, 
    "submitter_specimen_id": null, 
    "vcf_workflow_result_version": "v3"
}