{
    "_runs_": {
        "run_1458246587_fd7cf877-ca7f-4dab-98e7-854d91eb2ded": {
            "downloading": {
                "gnos-download_time": 126, 
                "start": 1458276612, 
                "stop": 1458276738, 
                "time": 126
            }
        }
    }, 
    "aliquot_id": null, 
    "available_repos": [
        {
            "https://gtrepo-osdc-icgc.annailabs.com/": {
                "file_md5sum": "6ab2478fb19979773a53bb6716c51aae", 
                "file_size": 36047
            }
        }
    ], 
    "data_type": "Muse-VCF", 
    "files": [
        {
            "file_md5sum": "7e062279f74eada6bb7a73522a67f776", 
            "file_name": "650fe009-da01-4717-89df-9c95fafe3d7e.MUSE_1-0rc-vcf.20151023.somatic.snv_mnv.vcf.gz", 
            "file_size": 190854, 
            "object_id": ""
        }, 
        {
            "file_md5sum": "311f30e1c868356f40370e7615bd0484", 
            "file_name": "650fe009-da01-4717-89df-9c95fafe3d7e.MUSE_1-0rc-vcf.20151023.somatic.snv_mnv.vcf.gz.idx", 
            "file_size": 105462, 
            "object_id": ""
        }, 
        {
            "file_md5sum": "6ab2478fb19979773a53bb6716c51aae", 
            "file_name": "509df0d9-8788-405d-8125-0528e306bc5e.xml", 
            "file_size": 36047, 
            "object_id": ""
        }
    ], 
    "gnos_id": "509df0d9-8788-405d-8125-0528e306bc5e", 
    "gnos_repo": [
        "https://gtrepo-osdc-icgc.annailabs.com/"
    ], 
    "project_code": "MALY-DE", 
    "specimen_type": null, 
    "submitter_donor_id": "4175837", 
    "submitter_sample_id": null, 
    "submitter_specimen_id": null, 
    "vcf_workflow_result_version": "v1"
}