{
    "aliquot_id": null, 
    "available_repos": [
        {
            "https://gtrepo-osdc-icgc.annailabs.com/": {
                "file_md5sum": "fb0f0f1c7911af35199d8530f8d730b1", 
                "file_size": 35953
            }
        }
    ], 
    "data_type": "Muse-VCF", 
    "files": [
        {
            "file_md5sum": "95112aa8db3c00c0ea6f5a57a289438b", 
            "file_name": "391a949d-217a-472c-a6d4-80e548039684.MUSE_1-0rc-vcf.20151023.somatic.snv_mnv.vcf.gz", 
            "file_size": 47106, 
            "object_id": "ffa795c0-a275-5ba8-9811-9437785951cf"
        }, 
        {
            "file_md5sum": "a5633e480752c3cc05e8293b13c05da6", 
            "file_name": "391a949d-217a-472c-a6d4-80e548039684.MUSE_1-0rc-vcf.20151023.somatic.snv_mnv.vcf.gz.idx", 
            "file_size": 30545, 
            "object_id": "33e9652b-094f-5399-8180-903af7bd7a7a"
        }, 
        {
            "file_md5sum": "fb0f0f1c7911af35199d8530f8d730b1", 
            "file_name": "7cb2bee7-ea20-487c-8a20-1b270e76f987.xml", 
            "file_size": 35953, 
            "object_id": "96f04548-6c39-58ef-b160-c3801ed65721"
        }
    ], 
    "gnos_id": "7cb2bee7-ea20-487c-8a20-1b270e76f987", 
    "gnos_repo": [
        "https://gtrepo-osdc-icgc.annailabs.com/"
    ], 
    "project_code": "PBCA-DE", 
    "specimen_type": null, 
    "submitter_donor_id": "ICGC_MB165", 
    "submitter_sample_id": null, 
    "submitter_specimen_id": null, 
    "vcf_workflow_result_version": "v1"
}