{
    "aliquot_id": "363d3a59-dce3-408d-a736-5c29ba9f9b6d", 
    "available_repos": [
        {
            "https://gtrepo-osdc-icgc.annailabs.com/": {
                "file_md5sum": "a2e0eb709302f24347fc622ee94e7bb9", 
                "file_size": 31584
            }
        }
    ], 
    "data_type": "Consensus-somatic-SNV_MNV", 
    "files": [
        {
            "file_md5sum": "5308bb7679d26edd59e3ba8db9b81a45", 
            "file_name": "363d3a59-dce3-408d-a736-5c29ba9f9b6d.consensus.20160830.somatic.snv_mnv.vcf.gz", 
            "file_size": 36247, 
            "object_id": "ac59d98c-c61c-5fce-a1f4-186975b274b5"
        }, 
        {
            "file_md5sum": "f623c7d0a205994c72d5d0c9bb2668cc", 
            "file_name": "363d3a59-dce3-408d-a736-5c29ba9f9b6d.consensus.20160830.somatic.snv_mnv.vcf.gz.tbi", 
            "file_size": 23187, 
            "object_id": "ee8a2365-54f9-52a3-9e0a-3f39302e708d"
        }, 
        {
            "file_md5sum": "a2e0eb709302f24347fc622ee94e7bb9", 
            "file_name": "2fcf8c80-3612-4777-8726-7e0a394f8be1.xml", 
            "file_size": 31584, 
            "object_id": "3bfd83aa-18f7-57fd-bcf5-c5878e4e51f2"
        }
    ], 
    "gnos_id": "2fcf8c80-3612-4777-8726-7e0a394f8be1", 
    "gnos_repo": [
        "https://gtrepo-osdc-icgc.annailabs.com/"
    ], 
    "project_code": "PBCA-DE", 
    "specimen_type": null, 
    "submitter_donor_id": "ICGC_PA30", 
    "submitter_sample_id": null, 
    "submitter_specimen_id": "363d3a59-dce3-408d-a736-5c29ba9f9b6d", 
    "vcf_workflow_result_version": "v1"
}