{
    "aliquot_id": "6d2a5ee7-9e46-4c09-a982-7b61b5d9bdea", 
    "available_repos": [
        {
            "https://gtrepo-osdc-icgc.annailabs.com/": {
                "file_md5sum": "701790c2cdc2a5d8537b59d4e0523cc0", 
                "file_size": 31544
            }
        }
    ], 
    "data_type": "Consensus-somatic-INDEL", 
    "files": [
        {
            "file_md5sum": "fa670691811e5a2053343b1414d721a8", 
            "file_name": "6d2a5ee7-9e46-4c09-a982-7b61b5d9bdea.consensus.20160830.somatic.indel.vcf.gz", 
            "file_size": 43147, 
            "object_id": "446f5d83-5b2a-5f52-bd79-74669045eee0"
        }, 
        {
            "file_md5sum": "0aed22cf385b265afcb5e4a436abb59d", 
            "file_name": "6d2a5ee7-9e46-4c09-a982-7b61b5d9bdea.consensus.20160830.somatic.indel.vcf.gz.tbi", 
            "file_size": 20248, 
            "object_id": "ed07d5ad-616c-52ae-a4fd-bada89d8b0dc"
        }, 
        {
            "file_md5sum": "701790c2cdc2a5d8537b59d4e0523cc0", 
            "file_name": "d21e3cd4-a860-4846-bf81-14e9f1a0e2f1.xml", 
            "file_size": 31544, 
            "object_id": "e33daf00-5645-5290-b2d9-466b8af68d0b"
        }
    ], 
    "gnos_id": "d21e3cd4-a860-4846-bf81-14e9f1a0e2f1", 
    "gnos_repo": [
        "https://gtrepo-osdc-icgc.annailabs.com/"
    ], 
    "project_code": "PBCA-DE", 
    "specimen_type": null, 
    "submitter_donor_id": "ICGC_MB160", 
    "submitter_sample_id": null, 
    "submitter_specimen_id": "6d2a5ee7-9e46-4c09-a982-7b61b5d9bdea", 
    "vcf_workflow_result_version": "v1"
}