{
    "aliquot_id": "3f3aff50-d71b-44af-85d4-f81e813ea420", 
    "available_repos": [
        {
            "https://gtrepo-osdc-icgc.annailabs.com/": {
                "file_md5sum": "7eae7bc0fc203fdac93e302060634eb7", 
                "file_size": 31390
            }
        }
    ], 
    "data_type": "Consensus-somatic-SNV_MNV", 
    "files": [
        {
            "file_md5sum": "af4888a8e4d4fb56ea84be42c3f816c6", 
            "file_name": "3f3aff50-d71b-44af-85d4-f81e813ea420.consensus.20160830.somatic.snv_mnv.vcf.gz", 
            "file_size": 40535, 
            "object_id": "888f8838-64be-5fc8-9e66-f9f1e04caa63"
        }, 
        {
            "file_md5sum": "b9037c2c44ce3c49748c39665b74d33f", 
            "file_name": "3f3aff50-d71b-44af-85d4-f81e813ea420.consensus.20160830.somatic.snv_mnv.vcf.gz.tbi", 
            "file_size": 26418, 
            "object_id": "6a83dccc-b067-5ed7-8b8a-80c7535eb3ca"
        }, 
        {
            "file_md5sum": "7eae7bc0fc203fdac93e302060634eb7", 
            "file_name": "ff152fb3-f15e-4dbd-a535-cee39b40c56a.xml", 
            "file_size": 31390, 
            "object_id": "3a5768d5-abce-574c-960f-d53560b449bc"
        }
    ], 
    "gnos_id": "ff152fb3-f15e-4dbd-a535-cee39b40c56a", 
    "gnos_repo": [
        "https://gtrepo-osdc-icgc.annailabs.com/"
    ], 
    "project_code": "PBCA-DE", 
    "specimen_type": null, 
    "submitter_donor_id": "ICGC_MB7", 
    "submitter_sample_id": null, 
    "submitter_specimen_id": "3f3aff50-d71b-44af-85d4-f81e813ea420", 
    "vcf_workflow_result_version": "v1"
}