{
    "aliquot_id": "4c755527-3b5d-4d36-822d-990aa1003d6a", 
    "available_repos": [
        {
            "https://gtrepo-osdc-icgc.annailabs.com/": {
                "file_md5sum": "880921e98c62b6832c71d348c4b5cb08", 
                "file_size": 31806
            }
        }
    ], 
    "data_type": "Consensus-somatic-INDEL", 
    "files": [
        {
            "file_md5sum": "69dc3a19cb50df1f1918548830e7c451", 
            "file_name": "4c755527-3b5d-4d36-822d-990aa1003d6a.consensus.20160830.somatic.indel.vcf.gz", 
            "file_size": 24097, 
            "object_id": "bc913cf0-8730-5bbc-bfad-aa264ebfa1e4"
        }, 
        {
            "file_md5sum": "11a05ac29c417a7a2d5f87bf5d9a558f", 
            "file_name": "4c755527-3b5d-4d36-822d-990aa1003d6a.consensus.20160830.somatic.indel.vcf.gz.tbi", 
            "file_size": 13033, 
            "object_id": "cb42a0da-3cd1-58ff-b587-52683cf80e33"
        }, 
        {
            "file_md5sum": "880921e98c62b6832c71d348c4b5cb08", 
            "file_name": "6f81c17f-e58c-455a-ae5d-4d45788985e1.xml", 
            "file_size": 31806, 
            "object_id": "bde3fc3e-d908-54f0-abd3-1d9144e782ee"
        }
    ], 
    "gnos_id": "6f81c17f-e58c-455a-ae5d-4d45788985e1", 
    "gnos_repo": [
        "https://gtrepo-osdc-icgc.annailabs.com/"
    ], 
    "project_code": "EOPC-DE", 
    "specimen_type": null, 
    "submitter_donor_id": "EOPC-036", 
    "submitter_sample_id": null, 
    "submitter_specimen_id": "4c755527-3b5d-4d36-822d-990aa1003d6a", 
    "vcf_workflow_result_version": "v1"
}