{
    "aliquot_id": "02078f77-2b35-4fa3-ab02-2c017181295e", 
    "available_repos": [
        {
            "https://gtrepo-osdc-icgc.annailabs.com/": {
                "file_md5sum": "8ca952bda6ae5e6f6856f9cce306e2dd", 
                "file_size": 31832
            }
        }
    ], 
    "data_type": "Consensus-somatic-SNV_MNV", 
    "files": [
        {
            "file_md5sum": "93afd1be3c4addd56683cef7032149a9", 
            "file_name": "02078f77-2b35-4fa3-ab02-2c017181295e.consensus.20160830.somatic.snv_mnv.vcf.gz", 
            "file_size": 17978, 
            "object_id": "2c406529-629c-5333-af54-b98d64061ed8"
        }, 
        {
            "file_md5sum": "1c94e9389448c1ef93784a8ca47ad30d", 
            "file_name": "02078f77-2b35-4fa3-ab02-2c017181295e.consensus.20160830.somatic.snv_mnv.vcf.gz.tbi", 
            "file_size": 13313, 
            "object_id": "a1669b2a-a661-5e51-9893-c2db0d136e2c"
        }, 
        {
            "file_md5sum": "8ca952bda6ae5e6f6856f9cce306e2dd", 
            "file_name": "a0c158bf-dea4-4198-96a4-c4c15f0f0b72.xml", 
            "file_size": 31832, 
            "object_id": "c1cb3ded-db31-5630-816d-e5b06cd00686"
        }
    ], 
    "gnos_id": "a0c158bf-dea4-4198-96a4-c4c15f0f0b72", 
    "gnos_repo": [
        "https://gtrepo-osdc-icgc.annailabs.com/"
    ], 
    "project_code": "PBCA-DE", 
    "specimen_type": null, 
    "submitter_donor_id": "ICGC_PA39", 
    "submitter_sample_id": null, 
    "submitter_specimen_id": "02078f77-2b35-4fa3-ab02-2c017181295e", 
    "vcf_workflow_result_version": "v1"
}