{
    "aliquot_id": "19b6b9d6-6912-4b85-a4bf-52014bcb170b", 
    "available_repos": [
        {
            "https://gtrepo-osdc-icgc.annailabs.com/": {
                "file_md5sum": "d7fcd426d3c264816548560de9146418", 
                "file_size": 32635
            }
        }
    ], 
    "data_type": "Consensus-somatic-SNV_MNV", 
    "files": [
        {
            "file_md5sum": "65034f33f51272507a227bcec5e5ec65", 
            "file_name": "19b6b9d6-6912-4b85-a4bf-52014bcb170b.consensus.20160830.somatic.snv_mnv.vcf.gz", 
            "file_size": 49230, 
            "object_id": "8a97a2c1-e4f7-5b79-874d-b7be4985eeeb"
        }, 
        {
            "file_md5sum": "642dd9f19c761b5cc4f1b7264c7b0f64", 
            "file_name": "19b6b9d6-6912-4b85-a4bf-52014bcb170b.consensus.20160830.somatic.snv_mnv.vcf.gz.tbi", 
            "file_size": 31019, 
            "object_id": "36b3531b-5043-56a4-85f0-44de50658f45"
        }, 
        {
            "file_md5sum": "d7fcd426d3c264816548560de9146418", 
            "file_name": "cf42c353-19ad-4f1e-859b-a33fb8ef15a2.xml", 
            "file_size": 32635, 
            "object_id": "ef0910a7-75df-510e-b12d-3e7816799f4d"
        }
    ], 
    "gnos_id": "cf42c353-19ad-4f1e-859b-a33fb8ef15a2", 
    "gnos_repo": [
        "https://gtrepo-osdc-icgc.annailabs.com/"
    ], 
    "project_code": "PBCA-DE", 
    "specimen_type": null, 
    "submitter_donor_id": "ICGC_MB36", 
    "submitter_sample_id": null, 
    "submitter_specimen_id": "19b6b9d6-6912-4b85-a4bf-52014bcb170b", 
    "vcf_workflow_result_version": "v1"
}