{
    "aliquot_id": "909f3c5d-89fc-419b-a654-75ac1dbb149f", 
    "available_repos": [
        {
            "https://gtrepo-osdc-icgc.annailabs.com/": {
                "file_md5sum": "8862fa77cae08f1b608a92d5340c802e", 
                "file_size": 31530
            }
        }
    ], 
    "data_type": "Consensus-somatic-INDEL", 
    "files": [
        {
            "file_md5sum": "62b1d5ddb5cbfcbbd1e26d6fccc963cd", 
            "file_name": "909f3c5d-89fc-419b-a654-75ac1dbb149f.consensus.20160830.somatic.indel.vcf.gz", 
            "file_size": 13496, 
            "object_id": "fc4d64ae-cade-5a5c-98be-c73b5512c570"
        }, 
        {
            "file_md5sum": "67a0598875674f4ff06ea19001e5cd0f", 
            "file_name": "909f3c5d-89fc-419b-a654-75ac1dbb149f.consensus.20160830.somatic.indel.vcf.gz.tbi", 
            "file_size": 9028, 
            "object_id": "2d52f4a5-3288-50ef-bca2-e69dc9dbcb2c"
        }, 
        {
            "file_md5sum": "8862fa77cae08f1b608a92d5340c802e", 
            "file_name": "f888c2cd-6e1a-4fa5-8333-698d26fd85d7.xml", 
            "file_size": 31530, 
            "object_id": "30f06361-876e-5e2b-abc4-fecac5dbfea8"
        }
    ], 
    "gnos_id": "f888c2cd-6e1a-4fa5-8333-698d26fd85d7", 
    "gnos_repo": [
        "https://gtrepo-osdc-icgc.annailabs.com/"
    ], 
    "project_code": "PBCA-DE", 
    "specimen_type": null, 
    "submitter_donor_id": "ICGC_MB185", 
    "submitter_sample_id": null, 
    "submitter_specimen_id": "909f3c5d-89fc-419b-a654-75ac1dbb149f", 
    "vcf_workflow_result_version": "v1"
}