{
    "_runs_": {
        "run_1493648426_0d2c4d64-eee6-4713-974c-a437f69cff2b": {
            "downloading": {
                "gnos-download_time": 23, 
                "start": 1493649153, 
                "stop": 1493649176, 
                "time": 23
            }, 
            "uploading": {
                "copy_meta_time": 2, 
                "start": 1493649181, 
                "stop": 1493649208, 
                "time": 27, 
                "upload_time": 25
            }
        }
    }, 
    "aliquot_id": "9be1246b-3dc1-4928-8b89-2d5ed0c866e8", 
    "available_repos": [
        {
            "https://gtrepo-osdc-icgc.annailabs.com/": {
                "file_md5sum": "a7f2ac66fb786f9b20a6d2217a1d2ccf", 
                "file_size": 33111
            }
        }
    ], 
    "data_type": "Consensus-somatic-INDEL", 
    "files": [
        {
            "file_md5sum": "b0f752fc60ba5ea864b8a0baab74dd44", 
            "file_name": "9be1246b-3dc1-4928-8b89-2d5ed0c866e8.consensus.20161006.somatic.indel.vcf.gz", 
            "file_size": 40289, 
            "object_id": "de24599a-196c-5977-b555-b70dcb65c134"
        }, 
        {
            "file_md5sum": "92e7effb0bf3832d76a089e998a4b62d", 
            "file_name": "9be1246b-3dc1-4928-8b89-2d5ed0c866e8.consensus.20161006.somatic.indel.vcf.gz.tbi", 
            "file_size": 20091, 
            "object_id": "0b8bc97e-0f48-515d-99c8-e8a1ce63284b"
        }, 
        {
            "file_md5sum": "a7f2ac66fb786f9b20a6d2217a1d2ccf", 
            "file_name": "569c377c-88cb-4ebc-8edc-3dc045837064.xml", 
            "file_size": 33111, 
            "object_id": "418f7f19-1012-588b-a59f-f719103cd41b"
        }
    ], 
    "gnos_id": "569c377c-88cb-4ebc-8edc-3dc045837064", 
    "gnos_repo": [
        "https://gtrepo-osdc-icgc.annailabs.com/"
    ], 
    "project_code": "PBCA-DE", 
    "specimen_type": null, 
    "submitter_donor_id": "ICGC_MB66", 
    "submitter_sample_id": null, 
    "submitter_specimen_id": "9be1246b-3dc1-4928-8b89-2d5ed0c866e8", 
    "vcf_workflow_result_version": "v1"
}