{
    "_runs_": {
        "run_1473902443_d1e1ef91-aef7-429e-aa84-08094051c063": {
            "downloading": {
                "gnos-download_time": 25, 
                "start": 1473946399, 
                "stop": 1473946424, 
                "time": 25
            }, 
            "uploading": {
                "copy_meta_time": 1, 
                "start": 1473946435, 
                "stop": 1473946461, 
                "time": 26, 
                "upload_time": 25
            }
        }
    }, 
    "aliquot_id": "d733cf1a-4c42-4def-b6cb-5ef2c6a27fcd", 
    "available_repos": [
        {
            "https://gtrepo-osdc-icgc.annailabs.com/": {
                "file_md5sum": "30402d3b35b543d330f102bf565c3c5a", 
                "file_size": 31599
            }
        }
    ], 
    "data_type": "Consensus-somatic-INDEL", 
    "files": [
        {
            "file_md5sum": "20c3dd84f4014bc7d9ed65800b71e6a9", 
            "file_name": "d733cf1a-4c42-4def-b6cb-5ef2c6a27fcd.consensus.20160830.somatic.indel.vcf.gz", 
            "file_size": 97683, 
            "object_id": "0e88fcfd-fd81-50fe-915e-5f8948887b59"
        }, 
        {
            "file_md5sum": "1fc96d98320a119fcc771566a227d3e3", 
            "file_name": "d733cf1a-4c42-4def-b6cb-5ef2c6a27fcd.consensus.20160830.somatic.indel.vcf.gz.tbi", 
            "file_size": 44074, 
            "object_id": "39d6eaef-bf5f-5fdd-a3d3-88262e587756"
        }, 
        {
            "file_md5sum": "30402d3b35b543d330f102bf565c3c5a", 
            "file_name": "7da4f268-5bd3-47ee-a773-0386823404ba.xml", 
            "file_size": 31599, 
            "object_id": "4d493afb-3560-531d-95a3-8fd9d40bc377"
        }
    ], 
    "gnos_id": "7da4f268-5bd3-47ee-a773-0386823404ba", 
    "gnos_repo": [
        "https://gtrepo-osdc-icgc.annailabs.com/"
    ], 
    "project_code": "MALY-DE", 
    "specimen_type": null, 
    "submitter_donor_id": "4166706", 
    "submitter_sample_id": null, 
    "submitter_specimen_id": "d733cf1a-4c42-4def-b6cb-5ef2c6a27fcd", 
    "vcf_workflow_result_version": "v1"
}